statsnet_python_sdk/__init__.py
statsnet_python_sdk/client.py
statsnet_python_sdk/exceptions.py
statsnet_python_sdk/models.py
statsnet_python_sdk/validations.py
statsnet_python_sdk-1.1.5.dist-info/METADATA
statsnet_python_sdk-1.1.5.dist-info/WHEEL
statsnet_python_sdk-1.1.5.dist-info/RECORD
