Metadata-Version: 2.1
Name: statsnet-python-sdk
Version: 1.1.5
Summary: Python SDK for statsnet.co
Author: statsnet
Author-email: hi@statsnet.co
Requires-Python: >=3.8,<4.0
Classifier: Programming Language :: Python :: 3
Classifier: Programming Language :: Python :: 3.8
Classifier: Programming Language :: Python :: 3.9
Classifier: Programming Language :: Python :: 3.10
Classifier: Programming Language :: Python :: 3.11
Classifier: Programming Language :: Python :: 3.12
Requires-Dist: httpx (==0.27.0)
